odoo8_addon_stock_putaway_product-8.0.1.0.1-py2.7-nspkg.pth
odoo8_addon_stock_putaway_product-8.0.1.0.1.dist-info/top_level.txt
odoo8_addon_stock_putaway_product-8.0.1.0.1.dist-info/WHEEL
odoo8_addon_stock_putaway_product-8.0.1.0.1.dist-info/RECORD
odoo8_addon_stock_putaway_product-8.0.1.0.1.dist-info/metadata.json
odoo8_addon_stock_putaway_product-8.0.1.0.1.dist-info/DESCRIPTION.rst
odoo8_addon_stock_putaway_product-8.0.1.0.1.dist-info/METADATA
odoo8_addon_stock_putaway_product-8.0.1.0.1.dist-info/namespace_packages.txt
odoo_addons/stock_putaway_product/__openerp__.py
odoo_addons/stock_putaway_product/__init__.py
odoo_addons/stock_putaway_product/README.rst
odoo_addons/stock_putaway_product/security/ir.model.access.csv
odoo_addons/stock_putaway_product/models/product.py
odoo_addons/stock_putaway_product/models/__init__.py
odoo_addons/stock_putaway_product/models/product_putaway.py
odoo_addons/stock_putaway_product/i18n/ja.po
odoo_addons/stock_putaway_product/i18n/nl_NL.po
odoo_addons/stock_putaway_product/i18n/lv.po
odoo_addons/stock_putaway_product/i18n/zh_CN.po
odoo_addons/stock_putaway_product/i18n/nb_NO.po
odoo_addons/stock_putaway_product/i18n/uk.po
odoo_addons/stock_putaway_product/i18n/es_AR.po
odoo_addons/stock_putaway_product/i18n/ko.po
odoo_addons/stock_putaway_product/i18n/tr_TR.po
odoo_addons/stock_putaway_product/i18n/ru.po
odoo_addons/stock_putaway_product/i18n/gl_ES.po
odoo_addons/stock_putaway_product/i18n/pt.po
odoo_addons/stock_putaway_product/i18n/fr_CH.po
odoo_addons/stock_putaway_product/i18n/it.po
odoo_addons/stock_putaway_product/i18n/es_CL.po
odoo_addons/stock_putaway_product/i18n/es.po
odoo_addons/stock_putaway_product/i18n/nl_BE.po
odoo_addons/stock_putaway_product/i18n/fr_FR.po
odoo_addons/stock_putaway_product/i18n/ar.po
odoo_addons/stock_putaway_product/i18n/lt.po
odoo_addons/stock_putaway_product/i18n/vi_VN.po
odoo_addons/stock_putaway_product/i18n/ro.po
odoo_addons/stock_putaway_product/i18n/tr.po
odoo_addons/stock_putaway_product/i18n/sr.po
odoo_addons/stock_putaway_product/i18n/es_PY.po
odoo_addons/stock_putaway_product/i18n/mk.po
odoo_addons/stock_putaway_product/i18n/hr.po
odoo_addons/stock_putaway_product/i18n/bg.po
odoo_addons/stock_putaway_product/i18n/es_EC.po
odoo_addons/stock_putaway_product/i18n/zh_TW.po
odoo_addons/stock_putaway_product/i18n/hu.po
odoo_addons/stock_putaway_product/i18n/fr_CA.po
odoo_addons/stock_putaway_product/i18n/gl.po
